CompArch/mp2/mipspipe.v
// Incomplete behavioral model of MIPS pipeline

module mipspipe(clock);
   // in_out
   input clock;

   // Instruction opcodes
   parameter LW = 6'b100011, SW = 6'b101011, BEQ = 6'b000100, nop = 32'b00000_100000, ALUop = 6'b0; 
   reg [31:0] PC, // Program counter
		  Regs[0:31],  // Register file
			  IMemory[0:1023], DMemory[0:1023], // Instruction and data memories
              IFIDIR, IDEXA, IDEXB, IDEXIR, EXMEMIR, EXMEMB, // pipeline latches
              EXMEMALUOut, MEMWBValue, MEMWBIR; // pipeline latches

   wire [4:0] IDEXrs, IDEXrt, EXMEMrd, MEMWBrd, MEMWBrt; // fields of pipeline latches
   wire [5:0] EXMEMop, MEMWBop, IDEXop; // opcodes
   wire [31:0] Ain, Bin; // ALU inputs

   // Define fields of pipeline latches
   assign IDEXrs = IDEXIR[25:21]; // rs field
   assign IDEXrt = IDEXIR[20:16]; // rt field
   assign EXMEMrd = EXMEMIR[15:11]; // rd field
   assign MEMWBrd = MEMWBIR[15:11]; // rd field
   assign MEMWBrt = MEMWBIR[20:16]; // rt field -- for loads
   assign EXMEMop = EXMEMIR[31:26]; // opcode
   assign MEMWBop = MEMWBIR[31:26]; // opcode
   assign IDEXop = IDEXIR[31:26]; // opcode

   // Inputs to the ALU come directly from the ID/EX pipeline latches
   assign Ain = IDEXA;
   assign Bin = IDEXB;
   reg [5:0] i; //used to initialize registers
   reg [10:0] j,k; //used to initialize registers

   initial begin
      PC = 0;
      IFIDIR = nop; 
      IDEXIR = nop; 
      EXMEMIR = nop; 
      MEMWBIR = nop; // no-ops placed in pipeline latches
      // test some instructions
      for (i=0;i<=31;i=i+1) Regs[i] = i; // initialize registers
      //IMemory[0] = 32'h8c210003;       //Lw
      //IMemory[1] = 32'hac020000;       //Sw
      //IMemory[2] = 32'h00642820;       //ALU
      IMemory[0] = 32'h00412820;       //(1) ADD $5, $2, $1
      IMemory[1] = nop;
      IMemory[2] = nop;
      IMemory[3] = nop;
      IMemory[4] = 32'h8CA30004;       //(2) LW $3, 4($5)
      IMemory[5] = nop;
      IMemory[6] = nop;
      IMemory[7] = 32'h8c420000;       //(3) LW $2, 0($2)
      IMemory[8] = 32'h00a31825;       //(4) OR $3, $5, $3
      IMemory[9] = nop;
      IMemory[10] = nop;
      IMemory[11] = nop;
      IMemory[12] = 32'haca30000;       //(5) SW $3, 0($5)
      for (j=13;j<=1023;j=j+1) IMemory[j] = nop;
      DMemory[0] = 32'hfffffff0;
      DMemory[1] = 32'hffffffff;
      for (k=8;k<=1023;k=k+1) DMemory[k] = 0;
   end
   
   always @ (posedge clock) 
   begin
      // FETCH: Fetch instruction & update PC
      IFIDIR <= IMemory[PC>>2];
	   PC <= PC + 4;
    
      // DECODE: Read registers 
      IDEXA <= Regs[IFIDIR[25:21]]; 
      IDEXB <= Regs[IFIDIR[20:16]]; // get two registers
      
	  IDEXIR <= IFIDIR; // pass along IR
      
      // EX: Address calculation or ALU operation
      if ((IDEXop==LW) |(IDEXop==SW)) // address calculation
         EXMEMALUOut <= IDEXA +{{16{IDEXIR[15]}}, IDEXIR[15:0]};
      else if (IDEXop==ALUop) begin // ALU operation
         case (IDEXIR[5:0]) // R-type instruction
           32: EXMEMALUOut <= Ain + Bin; // add operation
           37: EXMEMALUOut <= Ain | Bin; // OR Bit-wise operation
           default: ; // other R-type operations [to be implemented]
         endcase
      end
   
      EXMEMIR <= IDEXIR; EXMEMB <= IDEXB; //pass along the IR & B
   
      // MEM 
      if (EXMEMop==ALUop) MEMWBValue <= EXMEMALUOut; //pass along ALU result
      else if (EXMEMop == LW) MEMWBValue <= DMemory[EXMEMALUOut>>2]; // load
      else if (EXMEMop == SW) DMemory[EXMEMALUOut>>2] <=EXMEMB; // store
   
      MEMWBIR <= EXMEMIR; //pass along IR
   
      // WB 
      if ((MEMWBop==ALUop) & (MEMWBrd != 0)) // update registers if ALU operation and destination not 0
		Regs[MEMWBrd] <= MEMWBValue; // ALU operation
      else if ((MEMWBop == LW)& (MEMWBrt != 0)) // Update registers if load and destination not 0
		Regs[MEMWBrt] <= MEMWBValue;
    end

endmodule

CompArch/mp2/test_mipspipe.v
//
// Test bench for the mipspipe
// Boram Lee
//
  
`include "mipspipe.v"
  
module test_mipspipe;
  
  reg clock;
  reg [4:0] clock_cycle;  //max should be 31 instead of 15 now

// instantiate pipeline module
  mipspipe u_mipspipe(clock);
 
// initialize clock and cycle counter 
  initial begin
    clock = 0;
    clock_cycle=5'h0;
    #260  $finish;
  end
  
// 10 unit clock cycle
  always 
    #5 clock = ~clock;

  always @(posedge clock)
     begin
       clock_cycle=clock_cycle+1;
     end


// display contents of pipeline latches at the end of each clock cycle
  always @(negedge clock) 
     begin
     $display("\n\nclock cycle = %d",clock_cycle," (time = %1.0t)",$time);
     $display("IF/ID registers\n\t IF/ID.PC+4 = %h, IF/ID.IR = %h \n", u_mipspipe.PC, u_mipspipe.IFIDIR); 
     $display("ID/EX registers\n\t ID/EX.rs = %d, ID/EX.rt = %d",u_mipspipe.IDEXrs,u_mipspipe.IDEXrt,"\n\t ID/EX.A = %h, ID/EX.B = %h",u_mipspipe.IDEXA,u_mipspipe.IDEXB);
     $display("\t ID/EX.op = %h\n",u_mipspipe.IDEXop);
     $display("EX/MEM registers\n\t EX/MEM.rs = %d, EX/MEM.rt = %d",u_mipspipe.IDEXrs,u_mipspipe.IDEXrt,"\n\t EX/MEM.ALUOut = %h, EX/MEM.ALUout = %h",u_mipspipe.EXMEMALUOut,u_mipspipe.EXMEMB);
     $display("\t EX/MEM.op = %h\n",u_mipspipe.EXMEMop);
     $display("MEM/WB registers\n\t MEM/WB.rd = %d, MEM/WB.rt = %d",u_mipspipe.MEMWBrd,u_mipspipe.MEMWBrt,"\n\t MEM/WB.value = %h",u_mipspipe.MEMWBValue);
     $display("\t EX/MEM.op = %h\n",u_mipspipe.MEMWBop);
     end
      
// log to a vcd (variable change dump) file
   initial
      begin
      $dumpfile("test_mipspipe.vcd");
      $dumpvars;
   end

endmodule

CompArch/mp2/test_mipspipe.vcd
$date
	Fri Apr 14 20:25:37 2023
$end
$version
	Icarus Verilog
$end
$timescale
	1s
$end
$scope module test_mipspipe $end
$var reg 1 ! clock $end
$var reg 5 " clock_cycle [4:0] $end
$scope module u_mipspipe $end
$var wire 32 # Ain [31:0] $end
$var wire 32 $ Bin [31:0] $end
$var wire 1 ! clock $end
$var wire 5 % MEMWBrt [4:0] $end
$var wire 5 & MEMWBrd [4:0] $end
$var wire 6 ' MEMWBop [5:0] $end
$var wire 5 ( IDEXrt [4:0] $end
$var wire 5 ) IDEXrs [4:0] $end
$var wire 6 * IDEXop [5:0] $end
$var wire 5 + EXMEMrd [4:0] $end
$var wire 6 , EXMEMop [5:0] $end
$var reg 32 - EXMEMALUOut [31:0] $end
$var reg 32 . EXMEMB [31:0] $end
$var reg 32 / EXMEMIR [31:0] $end
$var reg 32 0 IDEXA [31:0] $end
$var reg 32 1 IDEXB [31:0] $end
$var reg 32 2 IDEXIR [31:0] $end
$var reg 32 3 IFIDIR [31:0] $end
$var reg 32 4 MEMWBIR [31:0] $end
$var reg 32 5 MEMWBValue [31:0] $end
$var reg 32 6 PC [31:0] $end
$var reg 6 7 i [5:0] $end
$var reg 11 8 j [10:0] $end
$var reg 11 9 k [10:0] $end
$upscope $end
$upscope $end
$enddefinitions $end
#0
$dumpvars
b10000000000 9
b10000000000 8
b100000 7
b0 6
bx 5
b100000 4
b100000 3
b100000 2
bx 1
bx 0
b100000 /
bx .
bx -
b0 ,
b0 +
b0 *
b0 )
b0 (
b0 '
b0 &
b0 %
bx $
bx #
b0 "
0!
$end
#5
b0 $
b0 1
b0 #
b0 0
b100 6
b10000010010100000100000 3
b1 "
1!
#10
0!
#15
b10 )
b1 (
b0 .
b0 -
b10000010010100000100000 2
b1 $
b1 1
b10 #
b10 0
b1000 6
b100000 3
b10 "
1!
#20
0!
#25
b101 +
b0 )
b0 (
b0 5
b1 .
b10000010010100000100000 /
b11 -
b100000 2
b0 $
b0 1
b0 #
b0 0
b1100 6
b11 "
1!
#30
0!
#35
b101 &
b1 %
b0 +
b10000010010100000100000 4
b11 5
b0 .
b100000 /
b0 -
b10000 6
b100 "
1!
#40
0!
#45
b0 &
b0 %
b100000 4
b0 5
b10100 6
b10001100101000110000000000000100 3
b101 "
1!
#50
0!
#55
b101 )
b11 (
b100011 *
b10001100101000110000000000000100 2
b11 $
b11 1
b11 #
b11 0
b11000 6
b100000 3
b110 "
1!
#60
0!
#65
b100011 ,
b0 )
b0 (
b0 *
b11 .
b10001100101000110000000000000100 /
b111 -
b100000 2
b0 $
b0 1
b0 #
b0 0
b11100 6
b111 "
1!
#70
0!
#75
b11 %
b100011 '
b0 ,
b10001100101000110000000000000100 4
b11111111111111111111111111111111 5
b0 .
b100000 /
b0 -
b100000 6
b10001100010000100000000000000000 3
b1000 "
1!
#80
0!
#85
b0 %
b0 '
b10 )
b10 (
b100011 *
b100000 4
b0 5
b10001100010000100000000000000000 2
b10 $
b10 1
b10 #
b10 0
b100100 6
b101000110001100000100101 3
b1001 "
1!
#90
0!
#95
b100011 ,
b101 )
b11 (
b0 *
b10 .
b10001100010000100000000000000000 /
b10 -
b101000110001100000100101 2
b11111111111111111111111111111111 $
b11111111111111111111111111111111 1
b11 #
b11 0
b101000 6
b100000 3
b1010 "
1!
#100
0!
#105
b10 %
b100011 '
b11 +
b0 ,
b0 )
b0 (
b10001100010000100000000000000000 4
b11111111111111111111111111110000 5
b11111111111111111111111111111111 .
b101000110001100000100101 /
b11111111111111111111111111111111 -
b100000 2
b0 $
b0 1
b0 #
b0 0
b101100 6
b1011 "
1!
#110
0!
#115
b11 &
b11 %
b0 '
b0 +
b101000110001100000100101 4
b11111111111111111111111111111111 5
b0 .
b100000 /
b0 -
b110000 6
b1100 "
1!
#120
0!
#125
b0 &
b0 %
b100000 4
b0 5
b110100 6
b10101100101000110000000000000000 3
b1101 "
1!
#130
0!
#135
b101 )
b11 (
b101011 *
b10101100101000110000000000000000 2
b11111111111111111111111111111111 $
b11111111111111111111111111111111 1
b11 #
b11 0
b111000 6
b100000 3
b1110 "
1!
#140
0!
#145
b101011 ,
b0 )
b0 (
b0 *
b11111111111111111111111111111111 .
b10101100101000110000000000000000 /
b11 -
b100000 2
b0 $
b0 1
b0 #
b0 0
b111100 6
b1111 "
1!
#150
0!
#155
b11 %
b101011 '
b0 ,
b10101100101000110000000000000000 4
b0 .
b100000 /
b0 -
b1000000 6
b10000 "
1!
#160
0!
#165
b0 %
b0 '
b100000 4
b1000100 6
b10001 "
1!
#170
0!
#175
b1001000 6
b10010 "
1!
#180
0!
#185
b1001100 6
b10011 "
1!
#190
0!
#195
b1010000 6
b10100 "
1!
#200
0!
#205
b1010100 6
b10101 "
1!
#210
0!
#215
b1011000 6
b10110 "
1!
#220
0!
#225
b1011100 6
b10111 "
1!
#230
0!
#235
b1100000 6
b11000 "
1!
#240
0!
#245
b1100100 6
b11001 "
1!
#250
0!
#255
b1101000 6
b11010 "
1!
