CompArch/mp3/mipspipe_mp3.v
// Complete behavioral model of MIPS pipeline
// Augmented by: Tarik Merzkani
// Ulya Karpuzcu Spring Apr 28, 2023 - CSCI 4203

module mipspipe_mp3 (clock);
  // in_out
  input clock;

  // Instruction opcodes
  parameter LW = 6'b100011, SW = 6'b101011, BEQ = 6'b000100, nop = 32'b00000_100000, ALUop = 6'b0;
  reg [31:0] PC, Regs[0:31], IMemory[0:1023], DMemory[0:1023], // instruction and data memories
  // array Regs is an array of 32 elements from 0 to 31, elements which consists of an array of 32 bits, from 31 to 0
             IFIDIR, IDEXA, IDEXB, IDEXIR, EXMEMIR, EXMEMB, // pipeline latches
             EXMEMALUOut, MEMWBValue, MEMWBIR;

  wire [4:0] IDEXrs, IDEXrt, EXMEMrd, MEMWBrd, MEMWBrt; // hold register fields
  wire [5:0] EXMEMop, MEMWBop, IDEXop; // hold opcodes
  wire [31:0] Ain, Bin; // ALU inputs

  // declare the bypass signals
  wire bypassAfromMEM, bypassAfromALUinWB, bypassBfromMEM, bypassBfromALUinWB, bypassAfromLWinWB, bypassBfromLWinWB;

   // Define fields of pipeline latches
   assign IDEXrs = IDEXIR[25:21]; // rs field
   assign IDEXrt = IDEXIR[20:16]; // rt field
   assign EXMEMrd = EXMEMIR[15:11]; // rd field
   assign MEMWBrd = MEMWBIR[15:11]; // rd field
   assign MEMWBrt = MEMWBIR[20:16]; // rt field -- for loads
   assign EXMEMop = EXMEMIR[31:26]; // opcode
   assign MEMWBop = MEMWBIR[31:26]; // opcode
   assign IDEXop = IDEXIR[31:26]; // opcode


// START C
  // The bypass to input A from the MEM stage for an ALU operation
  assign bypassAfromMEM = (IDEXrs == EXMEMrd) & (IDEXrs!=0) & (EXMEMop==ALUop);
  // The bypass to input B from the MEM stage for an ALU operation
  assign bypassBfromMEM = (IDEXrt == EXMEMrd) & (IDEXrt!=0) & (EXMEMop==ALUop);
  // The bypass to input A from the WB stage for an ALU operation
  assign bypassAfromALUinWB = (IDEXrs == MEMWBrd) & (IDEXrs!=0) & (MEMWBop==ALUop);
  // The bypass to input B from the WB stage for an ALU operation
  assign bypassBfromALUinWB = (IDEXrt == MEMWBrd) & (IDEXrt!=0) & (MEMWBop==ALUop); 
  // The bypass to input A from the WB stage for an LW operation
  assign bypassAfromLWinWB = (IDEXrs == MEMWBIR[20:16]) & (IDEXrs!=0) & (MEMWBop==LW);
  // The bypass to input B from the WB stage for an LW operation
  assign bypassBfromLWinWB = (IDEXrt == MEMWBIR[20:16]) & (IDEXrt!=0) & (MEMWBop==LW);

  // The A input to the ALU is bypassed from MEM if there is a bypass there,
  // Otherwise from WB if there is a bypass there, and otherwise comes from the IDEX register
  assign Ain = bypassAfromMEM ? EXMEMALUOut : (bypassAfromALUinWB | bypassAfromLWinWB)? MEMWBValue : IDEXA;

  // The B input to the ALU is bypassed from MEM if there is a bypass there,
  // Otherwise from WB if there is a bypass there, and otherwise comes from the IDEX register
  assign Bin = bypassBfromMEM ? EXMEMALUOut : (bypassBfromALUinWB | bypassBfromLWinWB) ? MEMWBValue : IDEXB;
// END C

  reg [5:0] i; // used to initialize latches
  reg [10:0] j,k; // used to initialize memories
  
  initial begin
    PC = 0;
    IFIDIR = nop; 
    IDEXIR = nop; 
    EXMEMIR = nop; 
    MEMWBIR = nop; // no-ops in pipeline latches
  
    for (i = 0;i<=31;i = i+1) Regs[i] = i; // initialize latches

    IMemory[0] = 32'h00412820;  // ADD $5, $2, $1
    IMemory[1] = 32'h8ca30004;  // LW $3, 4($5)
    IMemory[2] = 32'haca70005;  // SW $7, 5($5)
    IMemory[3] = 32'h00602020;  // ADD $4, $3, $0
    IMemory[4] = 32'h01093020;  // ADD $6, $8, $9
    IMemory[5] = 32'hac06000c;  // SW $6, 12($0)
    IMemory[6] = 32'h00c05020;  // ADD $10, $6, $0
    IMemory[7] = 32'h8c0b0010;  // LW $11, 16($0)
    IMemory[8] = 32'h00000020;  // ADD $0, $0, $0
    IMemory[9] = 32'h002b6020;  // ADD $12, $1, $11
    for (j=10; j<=1023; j=j+1) IMemory[j] = nop;
    
    DMemory[0] = 32'h00000000;
    DMemory[1] = 32'hffffffff;
    DMemory[2] = 32'h00000000;
    DMemory[3] = 32'h00000000;
    DMemory[4] = 32'hfffffffe;
    for (k=5; k<=1023; k=k+1) DMemory[k] = 0;
  end

  always @ (posedge clock) 
  begin
    
	// FETCH: Fetch instruction & update PC
    IFIDIR <= IMemory[PC>>2];
    PC <= PC + 4;

    // DECODE: Read registers
    IDEXA <= Regs[IFIDIR[25:21]]; 
    IDEXB <= Regs[IFIDIR[20:16]];
    IDEXIR <= IFIDIR; 

    // EX: Address calculation or ALU operation
    if ((IDEXop==LW) |(IDEXop==SW)) // address calculation & copy B
       EXMEMALUOut <= Ain +{{16{IDEXIR[15]}}, IDEXIR[15:0]};
    else if (IDEXop==ALUop) begin
       case (IDEXIR[5:0]) // R-type instruction
         32: EXMEMALUOut <= Ain + Bin; // add operation
         default: ; // other R-type operations: subtract, SLT, etc.
       endcase
    end
   
    EXMEMIR <= IDEXIR; 
    EXMEMB <= Bin; // pass along the IR & B register
   
    // MEM
    if (EXMEMop==ALUop) MEMWBValue <= EXMEMALUOut; // pass along ALU result
    else if (EXMEMop == LW) MEMWBValue <= DMemory[EXMEMALUOut>>2];
    else if (EXMEMop == SW) DMemory[EXMEMALUOut>>2] <=EXMEMB; // store
   
    MEMWBIR <= EXMEMIR; // pass along IR
   
    // WB 
    if ((MEMWBop==ALUop) & (MEMWBrd != 0)) // update latches if ALU operation and destination not 0
    Regs[MEMWBrd] <= MEMWBValue; // ALU operation
    else if ((MEMWBop == LW)& (MEMWBrt != 0)) // Update latches if load and destination not 0
    Regs[MEMWBrt] <= MEMWBValue;
  end

endmodule

CompArch/mp3/test_mipspipe_mp3.v
//
// Test bench for the mipspipe
// Boram Lee
//
  
`include "mipspipe_mp3.v"
  
module test_mipspipe;
  
  reg clock;
  reg [3:0] clock_cycle;      //change this so it's max is not 15 (4 bits)

// instantiate pipeline module
  mipspipe_mp3 u_mipspipe_mp3(clock);
 
// initialize clock and cycle counter 
  initial begin
    clock = 0;
    clock_cycle=4'h0;
    #160  $finish;    //Change so it doesn't change in a certain amount of units
    // 15 Cycles for this!
  end
  
// 10 unit clock cycle
  always 
    #5 clock = ~clock;

  always @(posedge clock)
     begin
       clock_cycle=clock_cycle+1;
     end


// display contents of pipeline latches at the end of each clock cycle
  always @(negedge clock) 
     begin
     $display("\n\nclock cycle = %d",clock_cycle," (time = %1.0t)",$time);
     $display("IF/ID registers\n\t IF/ID.PC+4 = %h, IF/ID.IR = %h \n", u_mipspipe_mp3.PC, u_mipspipe_mp3.IFIDIR); 
     $display("ID/EX registers\n\t ID/EX.rs = %d, ID/EX.rt = %d",u_mipspipe_mp3.IDEXrs,u_mipspipe_mp3.IDEXrt,"\n\t ID/EX.A = %h, ID/EX.B = %h",u_mipspipe_mp3.IDEXA,u_mipspipe_mp3.IDEXB);
     $display("\t ID/EX.op = %h\n",u_mipspipe_mp3.IDEXop);
     $display("EX/MEM registers\n\t EX/MEM.rs = %d, EX/MEM.rt = %d",u_mipspipe_mp3.IDEXrs,u_mipspipe_mp3.IDEXrt,"\n\t EX/MEM.ALUOut = %h, EX/MEM.ALUout = %h",u_mipspipe_mp3.EXMEMALUOut,u_mipspipe_mp3.EXMEMB);
     $display("\t EX/MEM.op = %h\n",u_mipspipe_mp3.EXMEMop);
     $display("MEM/WB registers\n\t MEM/WB.rd = %d, MEM/WB.rt = %d",u_mipspipe_mp3.MEMWBrd,u_mipspipe_mp3.MEMWBrt,"\n\t MEM/WB.value = %h",u_mipspipe_mp3.MEMWBValue);
     $display("\t EX/MEM.op = %h\n",u_mipspipe_mp3.MEMWBop);
     end
      
// log to a vcd (variable change dump) file
   initial
      begin
      $dumpfile("test_mipspipe.vcd");
      $dumpvars;
   end

endmodule

CompArch/mp3/test_mipspipe.vcd
$date
	Fri Apr 28 18:40:30 2023
$end
$version
	Icarus Verilog
$end
$timescale
	1s
$end
$scope module test_mipspipe $end
$var reg 1 ! clock $end
$var reg 4 " clock_cycle [3:0] $end
$scope module u_mipspipe_mp3 $end
$var wire 1 # bypassAfromALUinWB $end
$var wire 1 $ bypassAfromLWinWB $end
$var wire 1 % bypassAfromMEM $end
$var wire 1 & bypassBfromALUinWB $end
$var wire 1 ' bypassBfromLWinWB $end
$var wire 1 ( bypassBfromMEM $end
$var wire 1 ! clock $end
$var wire 5 ) MEMWBrt [4:0] $end
$var wire 5 * MEMWBrd [4:0] $end
$var wire 6 + MEMWBop [5:0] $end
$var wire 5 , IDEXrt [4:0] $end
$var wire 5 - IDEXrs [4:0] $end
$var wire 6 . IDEXop [5:0] $end
$var wire 5 / EXMEMrd [4:0] $end
$var wire 6 0 EXMEMop [5:0] $end
$var wire 32 1 Bin [31:0] $end
$var wire 32 2 Ain [31:0] $end
$var reg 32 3 EXMEMALUOut [31:0] $end
$var reg 32 4 EXMEMB [31:0] $end
$var reg 32 5 EXMEMIR [31:0] $end
$var reg 32 6 IDEXA [31:0] $end
$var reg 32 7 IDEXB [31:0] $end
$var reg 32 8 IDEXIR [31:0] $end
$var reg 32 9 IFIDIR [31:0] $end
$var reg 32 : MEMWBIR [31:0] $end
$var reg 32 ; MEMWBValue [31:0] $end
$var reg 32 < PC [31:0] $end
$var reg 6 = i [5:0] $end
$var reg 11 > j [10:0] $end
$var reg 11 ? k [10:0] $end
$upscope $end
$upscope $end
$enddefinitions $end
#0
$dumpvars
b10000000000 ?
b10000000000 >
b100000 =
b0 <
bx ;
b100000 :
b100000 9
b100000 8
bx 7
bx 6
b100000 5
bx 4
bx 3
bx 2
bx 1
b0 0
b0 /
b0 .
b0 -
b0 ,
b0 +
b0 *
b0 )
0(
0'
0&
0%
0$
0#
b0 "
0!
$end
#5
b0 1
b0 2
b0 7
b0 6
b100 <
b10000010010100000100000 9
b1 "
1!
#10
0!
#15
b1 1
b10 2
b10 -
b1 ,
b0 4
b0 3
b10000010010100000100000 8
b1 7
b10 6
b1000 <
b10001100101000110000000000000100 9
b10 "
1!
#20
0!
#25
1%
b11 1
b11 2
b101 /
b101 -
b11 ,
b100011 .
b0 ;
b1 4
b10000010010100000100000 5
b11 3
b10001100101000110000000000000100 8
b11 7
b101 6
b1100 <
b10101100101001110000000000000101 9
b11 "
1!
#30
0!
#35
1#
0%
b111 1
b101 *
b1 )
b0 /
b100011 0
b11 2
b111 ,
b101011 .
b10000010010100000100000 :
b11 ;
b11 4
b10001100101000110000000000000100 5
b111 3
b10101100101001110000000000000101 8
b111 7
b10000 <
b11000000010000000100000 9
b100 "
1!
#40
0!
#45
0#
1$
b11111111111111111111111111111111 2
b0 1
b0 *
b11 )
b100011 +
b101011 0
b11 -
b0 ,
b0 .
b10001100101000110000000000000100 :
b11111111111111111111111111111111 ;
b111 4
b10101100101001110000000000000101 5
b1000 3
b11000000010000000100000 8
b0 7
b11 6
b10100 <
b1000010010011000000100000 9
b101 "
1!
#50
0!
#55
b1000 2
0$
b1001 1
b111 )
b101011 +
b100 /
b0 0
b1000 -
b1001 ,
b10101100101001110000000000000101 :
b0 4
b11000000010000000100000 5
b11111111111111111111111111111111 3
b1000010010011000000100000 8
b1001 7
b1000 6
b11000 <
b10101100000001100000000000001100 9
b110 "
1!
#60
0!
#65
1(
b10001 1
b0 2
b100 *
b0 )
b0 +
b110 /
b0 -
b110 ,
b101011 .
b11000000010000000100000 :
b1001 4
b1000010010011000000100000 5
b10001 3
b10101100000001100000000000001100 8
b110 7
b0 6
b11100 <
b110000000101000000100000 9
b111 "
1!
#70
0!
#75
1#
0(
b10001 2
b110 *
b1001 )
b0 /
b101011 0
b0 1
b110 -
b0 ,
b0 .
b1000010010011000000100000 :
b10001 ;
b10001 4
b10101100000001100000000000001100 5
b1100 3
b110000000101000000100000 8
b0 7
b110 6
b100000 <
b10001100000010110000000000010000 9
b1000 "
1!
#80
0!
#85
b0 2
0#
b1011 1
b0 *
b110 )
b101011 +
b1010 /
b0 0
b0 -
b1011 ,
b100011 .
b10101100000001100000000000001100 :
b0 4
b110000000101000000100000 5
b10001 3
b10001100000010110000000000010000 8
b1011 7
b0 6
b100100 <
b100000 9
b1001 "
1!
#90
0!
#95
b0 1
b1010 *
b0 )
b0 +
b0 /
b100011 0
b0 ,
b0 .
b110000000101000000100000 :
b1011 4
b10001100000010110000000000010000 5
b10000 3
b100000 8
b0 7
b101000 <
b1010110110000000100000 9
b1010 "
1!
#100
0!
#105
1'
b11111111111111111111111111111110 1
b1 2
b0 *
b1011 )
b100011 +
b0 0
b1 -
b1011 ,
b10001100000010110000000000010000 :
b11111111111111111111111111111110 ;
b0 4
b100000 5
b0 3
b1010110110000000100000 8
b1011 7
b1 6
b101100 <
b100000 9
b1011 "
1!
#110
0!
#115
0'
b0 1
b0 2
b0 )
b0 +
b1100 /
b0 -
b0 ,
b100000 :
b0 ;
b11111111111111111111111111111110 4
b1010110110000000100000 5
b11111111111111111111111111111111 3
b100000 8
b0 7
b0 6
b110000 <
b1100 "
1!
#120
0!
#125
b1100 *
b1011 )
b0 /
b1010110110000000100000 :
b11111111111111111111111111111111 ;
b0 4
b100000 5
b0 3
b110100 <
b1101 "
1!
#130
0!
#135
b0 *
b0 )
b100000 :
b0 ;
b111000 <
b1110 "
1!
#140
0!
#145
b111100 <
b1111 "
1!
#150
0!
#155
b1000000 <
b0 "
1!
